maplerad_python/__init__.py
maplerad_python/auth.py
maplerad_python/bill.py
maplerad_python/collections.py
maplerad_python/counterparty.py
maplerad_python/customer.py
maplerad_python/exceptions.py
maplerad_python/fx.py
maplerad_python/identity.py
maplerad_python/institution.py
maplerad_python/issuing.py
maplerad_python/misc.py
maplerad_python/transactions.py
maplerad_python/transfer.py
maplerad_python/wallets.py
maplerad_python-0.0.3.dist-info/LICENSE.md
maplerad_python-0.0.3.dist-info/WHEEL
maplerad_python-0.0.3.dist-info/METADATA
maplerad_python-0.0.3.dist-info/RECORD
