Metadata-Version: 2.1
Name: maplerad-python
Version: 0.0.3
Summary: Maplerad python API wrapper
Home-page: https://maplerad.com
License: MIT
Keywords: maplerad,maplerad python package,maplerad python wrapper
Author: madvirus-ops
Author-email: edwinayabie1@gmail.com
Maintainer: madvirus-ops
Maintainer-email: edwinayabie1@gmail.com
Requires-Python: >=3.10,<4.0
Classifier: License :: OSI Approved :: MIT License
Classifier: Programming Language :: Python :: 3
Classifier: Programming Language :: Python :: 3.10
Requires-Dist: requests (>=2.31.0,<3.0.0)
Project-URL: Documentation, https://maplerad.dev/reference
Project-URL: Repository, https://github.com/madvirus-ops/maplerad-python
